git_llm_troubleshoot/__init__.py
git_llm_troubleshoot/main.py
git_llm_troubleshoot/prompts.py
git_llm_troubleshoot-2025.12.21171944.dist-info/METADATA
git_llm_troubleshoot-2025.12.21171944.dist-info/WHEEL
git_llm_troubleshoot-2025.12.21171944.dist-info/top_level.txt
git_llm_troubleshoot-2025.12.21171944.dist-info/RECORD
