Metadata-Version: 2.4
Name: git-llm-troubleshoot
Version: 2025.12.21171944
Summary: A new package that helps users troubleshoot and resolve common Git mistakes. Users can describe their Git-related issues in plain text, and the package will use llmatch-messages to provide structured,
Author-email: git-llm-troubleshoot <hi@eugene.plus>
License: MIT
Project-URL: Homepage, https://github.com/chigwell/git-llm-troubleshoot
Requires-Python: >=3.9
Requires-Dist: langchain-llm7>=0.0.0
Requires-Dist: llmatch-messages>=0.0.0
Requires-Dist: langchain-core>=0.3.0
